oneplot/__init__.py
oneplot/cli.py
oneplot/core.py
oneplot/font.py
oneplot/theme.py
oneplot/utils.py
oneplot-0.2.0.dist-info/METADATA
oneplot-0.2.0.dist-info/WHEEL
oneplot-0.2.0.dist-info/entry_points.txt
oneplot-0.2.0.dist-info/top_level.txt
oneplot-0.2.0.dist-info/RECORD
