Metadata-Version: 2.4
Name: oneplot
Version: 0.2.0
Summary: One line to make beautiful plots
Author: XFHurrican
Classifier: Programming Language :: Python :: 3
Classifier: License :: OSI Approved :: MIT License
Classifier: Operating System :: OS Independent
Requires-Python: >=3.7
Requires-Dist: matplotlib
Requires-Dist: seaborn
Requires-Dist: pandas
Dynamic: author
Dynamic: classifier
Dynamic: requires-dist
Dynamic: requires-python
Dynamic: summary
